cfundata/__init__.py
cfundata/utils.py
cfundata/data/sha256.json
cfundata-0.3.2.dist-info/METADATA
cfundata-0.3.2.dist-info/WHEEL
cfundata-0.3.2.dist-info/entry_points.txt
cfundata-0.3.2.dist-info/RECORD
